arduino_mcp/__init__.py
arduino_mcp/cli_wrapper.py
arduino_mcp/image_converter.py
arduino_mcp/platform_utils.py
arduino_mcp/port_detector.py
arduino_mcp/serial_manager.py
arduino_mcp/server.py
arduino_mcp-0.1.2.dist-info/METADATA
arduino_mcp-0.1.2.dist-info/WHEEL
arduino_mcp-0.1.2.dist-info/entry_points.txt
arduino_mcp-0.1.2.dist-info/RECORD
