Metadata-Version: 2.4
Name: arduino-mcp
Version: 0.1.2
Summary: MCP server for Arduino CLI interactions
Project-URL: Homepage, https://github.com/niradler/arduino-mcp
Project-URL: Repository, https://github.com/niradler/arduino-mcp
Project-URL: Documentation, https://github.com/niradler/arduino-mcp#readme
Project-URL: Issues, https://github.com/niradler/arduino-mcp/issues
Author-email: Nir Adler <me@niradler.com>
License: MIT
Keywords: arduino,arduino-cli,cli,fastmcp,mcp,model-context-protocol
Classifier: Development Status :: 3 - Alpha
Classifier: Intended Audience :: Developers
Classifier: License :: OSI Approved :: MIT License
Classifier: Programming Language :: Python :: 3
Classifier: Programming Language :: Python :: 3.10
Classifier: Programming Language :: Python :: 3.11
Classifier: Programming Language :: Python :: 3.12
Classifier: Topic :: Software Development :: Embedded Systems
Classifier: Topic :: System :: Hardware
Requires-Python: >=3.10
Requires-Dist: fastmcp>=0.1.0
Requires-Dist: pyserial>=3.5
